{
    "owner": "elastic",
    "repo": "eui",
    "base_hash": "b2893e2ca3cf6f0c04872da6959ed02c9e9ecd74",
    "golden_hash": "1b82dd83f5ab89d5e20aa2d9cae091355dd6bbaa",
    "golden_metrics": {
        "passed": 4588,
        "failed": 0,
        "skipped": 10,
        "total": 4598,
        "error": null
    },
    "base_metrics": {
        "passed": 4582,
        "failed": 0,
        "skipped": 10,
        "total": 4592,
        "error": null
    },
    "setup_image": "localhost/benchmark/elastic__eui-b2893e2c__setup",
    "runtime_image": "localhost/benchmark/elastic__eui-b2893e2c__runtime",
    "has_execution_environment": true,
    "reason_no_execution_environment": ""
}