{
    "owner": "keycloak",
    "repo": "keycloak",
    "base_hash": "808926b63e5db4a0e05f62dcb3738bd45e81d9fb",
    "golden_hash": "0be34d64e71cd80f6a72382b63ec454adaac5dc4",
    "golden_metrics": {
        "passed": 206,
        "failed": 2,
        "skipped": 2,
        "total": 210,
        "error": null
    },
    "base_metrics": {
        "passed": 206,
        "failed": 2,
        "skipped": 2,
        "total": 210,
        "error": null
    },
    "setup_image": "localhost/benchmark/keycloak__keycloak-808926b6__setup",
    "runtime_image": "localhost/benchmark/keycloak__keycloak-808926b6__runtime",
    "has_execution_environment": true,
    "reason_no_execution_environment": ""
}